ntanh/ParamsBase.py
ntanh/__init__.py
ntanh/image_augmentation.py
ntanh/image_calculation.py
ntanh/image_dupplicate_remove.py
ntanh/yolo_boxes.py
ntanh/IVIS_Data/__init__.py
ntanh/ImageProcessing/ImageProcessing.py
ntanh/ImageProcessing/resize_folder_image.py
ntanh/ImageProcessing/taPlotText.py
ntanh/Thoi_gian/taTimers.py
ntanh/YOLO_Logic/Labels_Filter.py
ntanh/YOLO_Logic/Logic_Comparison.py
ntanh/file_folder/Yolo_Data_Dupplicate_Remover.py
ntanh/file_folder/delete_files_in_directory.py
ntanh-3.7.2.dist-info/LICENSE
ntanh-3.7.2.dist-info/METADATA
ntanh-3.7.2.dist-info/WHEEL
ntanh-3.7.2.dist-info/entry_points.txt
ntanh-3.7.2.dist-info/top_level.txt
ntanh-3.7.2.dist-info/RECORD
