Metadata-Version: 2.1
Name: ntanh
Version: 3.7.2
Summary: Thư viện hữu ích của Tuấn Anh.
Home-page: https://pypi.org/project/ntanh/
Author: Tuấn Anh - Foxconn
Author-email: nt.anh.fai@gmail.com
License: MIT
Classifier: Programming Language :: Python :: 3
Classifier: License :: OSI Approved :: MIT License
Classifier: Operating System :: OS Independent
License-File: LICENSE
Requires-Dist: ruamel.yaml
Requires-Dist: pillow
Requires-Dist: scikit-image
Requires-Dist: lxml
Requires-Dist: numpy
Requires-Dist: tqdm
Requires-Dist: scikit-learn
